MANIFEST.in
README.rst
setup.py
Flask_Pypi_Proxy_Ext.egg-info/PKG-INFO
Flask_Pypi_Proxy_Ext.egg-info/SOURCES.txt
Flask_Pypi_Proxy_Ext.egg-info/dependency_links.txt
Flask_Pypi_Proxy_Ext.egg-info/not-zip-safe
Flask_Pypi_Proxy_Ext.egg-info/requires.txt
Flask_Pypi_Proxy_Ext.egg-info/top_level.txt
flask_pypi_proxy/__init__.py
flask_pypi_proxy/app.py
flask_pypi_proxy/utils.py
flask_pypi_proxy/templates/simple.html
flask_pypi_proxy/templates/simple_package.html
flask_pypi_proxy/views/__init__.py
flask_pypi_proxy/views/package.py
flask_pypi_proxy/views/pypi.py
flask_pypi_proxy/views/simple.py