Metadata-Version: 1.1
Name: Flask-Pypi-Proxy-Ext
Version: 0.5.1
Summary: A Pypi proxy
Home-page: https://github.com/tzulberti/Flask-PyPi-Proxy
Author: Tomas Zulberti
Author-email: tzulberti@gmail.com
License: BSD
Keywords: pypi flask proxy
Platform: UNKNOWN
Classifier: Development Status :: 3 - Alpha
Classifier: Environment :: Web Environment
Classifier: Intended Audience :: Developers
Classifier: Intended Audience :: System Administrators
Classifier: License :: OSI Approved :: BSD License
Classifier: Operating System :: OS Independent
Classifier: Programming Language :: Python :: 2.6
Classifier: Programming Language :: Python :: 2.7
Classifier: Topic :: Software Development :: Libraries :: Python Modules
